package com.google.android.gms.common.internal;

import android.os.Binder;
import android.os.IBinder;
import android.os.IInterface;
import android.os.Parcel;
import android.os.Parcelable.Creator;
import android.os.RemoteException;

public abstract interface zzv
  extends IInterface
{
  public abstract void zza(ResolveAccountResponse paramResolveAccountResponse)
    throws RemoteException;
  
  public static abstract class zza
    extends Binder
    implements zzv
  {
    public static zzv zzdw(IBinder paramIBinder)
    {
      if (paramIBinder == null) {
        paramIBinder = null;
      }
      for (;;)
      {
        return paramIBinder;
        IInterface localIInterface = paramIBinder.queryLocalInterface("com.google.android.gms.common.internal.IResolveAccountCallbacks");
        if ((localIInterface != null) && ((localIInterface instanceof zzv))) {
          paramIBinder = (zzv)localIInterface;
        } else {
          paramIBinder = new zza(paramIBinder);
        }
      }
    }
    
    public boolean onTransact(int paramInt1, Parcel paramParcel1, Parcel paramParcel2, int paramInt2)
      throws RemoteException
    {
      boolean bool;
      switch (paramInt1)
      {
      default: 
      case 1598968902: 
        for (bool = super.onTransact(paramInt1, paramParcel1, paramParcel2, paramInt2);; bool = true)
        {
          return bool;
          paramParcel2.writeString("com.google.android.gms.common.internal.IResolveAccountCallbacks");
        }
      }
      paramParcel1.enforceInterface("com.google.android.gms.common.internal.IResolveAccountCallbacks");
      if (paramParcel1.readInt() != 0) {}
      for (paramParcel1 = (ResolveAccountResponse)ResolveAccountResponse.CREATOR.createFromParcel(paramParcel1);; paramParcel1 = null)
      {
        zza(paramParcel1);
        paramParcel2.writeNoException();
        bool = true;
        break;
      }
    }
    
    private static class zza
      implements zzv
    {
      private IBinder zzajq;
      
      zza(IBinder paramIBinder)
      {
        this.zzajq = paramIBinder;
      }
      
      public IBinder asBinder()
      {
        return this.zzajq;
      }
      
      /* Error */
      public void zza(ResolveAccountResponse paramResolveAccountResponse)
        throws RemoteException
      {
        // Byte code:
        //   0: invokestatic 30	android/os/Parcel:obtain	()Landroid/os/Parcel;
        //   3: astore_2
        //   4: invokestatic 30	android/os/Parcel:obtain	()Landroid/os/Parcel;
        //   7: astore_3
        //   8: aload_2
        //   9: ldc 32
        //   11: invokevirtual 36	android/os/Parcel:writeInterfaceToken	(Ljava/lang/String;)V
        //   14: aload_1
        //   15: ifnull +41 -> 56
        //   18: aload_2
        //   19: iconst_1
        //   20: invokevirtual 40	android/os/Parcel:writeInt	(I)V
        //   23: aload_1
        //   24: aload_2
        //   25: iconst_0
        //   26: invokevirtual 46	com/google/android/gms/common/internal/ResolveAccountResponse:writeToParcel	(Landroid/os/Parcel;I)V
        //   29: aload_0
        //   30: getfield 18	com/google/android/gms/common/internal/zzv$zza$zza:zzajq	Landroid/os/IBinder;
        //   33: iconst_2
        //   34: aload_2
        //   35: aload_3
        //   36: iconst_0
        //   37: invokeinterface 52 5 0
        //   42: pop
        //   43: aload_3
        //   44: invokevirtual 55	android/os/Parcel:readException	()V
        //   47: aload_3
        //   48: invokevirtual 58	android/os/Parcel:recycle	()V
        //   51: aload_2
        //   52: invokevirtual 58	android/os/Parcel:recycle	()V
        //   55: return
        //   56: aload_2
        //   57: iconst_0
        //   58: invokevirtual 40	android/os/Parcel:writeInt	(I)V
        //   61: goto -32 -> 29
        //   64: astore_1
        //   65: aload_3
        //   66: invokevirtual 58	android/os/Parcel:recycle	()V
        //   69: aload_2
        //   70: invokevirtual 58	android/os/Parcel:recycle	()V
        //   73: aload_1
        //   74: athrow
        // Local variable table:
        //   start	length	slot	name	signature
        //   0	75	0	this	zza
        //   0	75	1	paramResolveAccountResponse	ResolveAccountResponse
        //   3	67	2	localParcel1	Parcel
        //   7	59	3	localParcel2	Parcel
        // Exception table:
        //   from	to	target	type
        //   8	14	64	finally
        //   18	29	64	finally
        //   29	47	64	finally
        //   56	61	64	finally
      }
    }
  }
}


/* Location:              C:\ApkExtract\classes-dex2jar.jar!\com\google\android\gms\common\internal\zzv.class
 * Java compiler version: 6 (50.0)
 * JD-Core Version:       0.7.1
 */